[
  {
    "image_path": "Dataset/30.jpeg",
    "inference_time": 1.618596076965332,
    "detections": [
      {
        "confidence": 0.897550642490387,
        "box": [
          269,
          484,
          498,
          540
        ],
        "aspect_ratio": 4.089285714285714,
        "area_percentage": 1.5808678500986193,
        "would_pass_normal_filters": {
          "aspect_ratio": true,
          "area_percentage": true,
          "confidence": true
        }
      },
      {
        "confidence": 0.028564460575580597,
        "box": [
          311,
          488,
          498,
          534
        ],
        "aspect_ratio": 4.065217391304348,
        "area_percentage": 1.0604043392504932,
        "would_pass_normal_filters": {
          "aspect_ratio": true,
          "area_percentage": true,
          "confidence": false
        }
      },
      {
        "confidence": 0.020580653101205826,
        "box": [
          268,
          495,
          497,
          532
        ],
        "aspect_ratio": 6.1891891891891895,
        "area_percentage": 1.0445019723865878,
        "would_pass_normal_filters": {
          "aspect_ratio": true,
          "area_percentage": true,
          "confidence": false
        }
      }
    ],
    "annotated_image": "direct_30.jpg",
    "high_confidence_count": 1,
    "normal_filter_pass_count": 1
  },
  {
    "image_path": "Dataset/44.jpeg",
    "inference_time": 1.5606577396392822,
    "detections": [
      {
        "confidence": 0.5151212215423584,
        "box": [
          498,
          145,
          560,
          172
        ],
        "aspect_ratio": 2.2962962962962963,
        "area_percentage": 0.6045503791982665,
        "would_pass_normal_filters": {
          "aspect_ratio": true,
          "area_percentage": true,
          "confidence": true
        }
      },
      {
        "confidence": 0.07430742681026459,
        "box": [
          65,
          0,
          167,
          117
        ],
        "aspect_ratio": 0.8717948717948718,
        "area_percentage": 4.309859154929577,
        "would_pass_normal_filters": {
          "aspect_ratio": false,
          "area_percentage": true,
          "confidence": false
        }
      },
      {
        "confidence": 0.041286103427410126,
        "box": [
          424,
          248,
          470,
          284
        ],
        "aspect_ratio": 1.2777777777777777,
        "area_percentage": 0.5980498374864572,
        "would_pass_normal_filters": {
          "aspect_ratio": true,
          "area_percentage": true,
          "confidence": false
        }
      },
      {
        "confidence": 0.02473132498562336,
        "box": [
          485,
          138,
          567,
          176
        ],
        "aspect_ratio": 2.1578947368421053,
        "area_percentage": 1.1253159985554353,
        "would_pass_normal_filters": {
          "aspect_ratio": true,
          "area_percentage": true,
          "confidence": false
        }
      },
      {
        "confidence": 0.017664898186922073,
        "box": [
          0,
          0,
          168,
          125
        ],
        "aspect_ratio": 1.344,
        "area_percentage": 7.583965330444204,
        "would_pass_normal_filters": {
          "aspect_ratio": true,
          "area_percentage": true,
          "confidence": false
        }
      },
      {
        "confidence": 0.01122682448476553,
        "box": [
          68,
          3,
          170,
          78
        ],
        "aspect_ratio": 1.36,
        "area_percentage": 2.76273022751896,
        "would_pass_normal_filters": {
          "aspect_ratio": true,
          "area_percentage": true,
          "confidence": false
        }
      }
    ],
    "annotated_image": "direct_44.jpg",
    "high_confidence_count": 1,
    "normal_filter_pass_count": 1
  },
  {
    "image_path": "Dataset/59.jpeg",
    "inference_time": 1.5598084926605225,
    "detections": [
      {
        "confidence": 0.03707385063171387,
        "box": [
          171,
          230,
          249,
          275
        ],
        "aspect_ratio": 1.7333333333333334,
        "area_percentage": 1.0204081632653061,
        "would_pass_normal_filters": {
          "aspect_ratio": true,
          "area_percentage": true,
          "confidence": false
        }
      },
      {
        "confidence": 0.0324261337518692,
        "box": [
          119,
          318,
          163,
          344
        ],
        "aspect_ratio": 1.6923076923076923,
        "area_percentage": 0.3325774754346183,
        "would_pass_normal_filters": {
          "aspect_ratio": true,
          "area_percentage": true,
          "confidence": false
        }
      }
    ],
    "annotated_image": "direct_59.jpg",
    "high_confidence_count": 0,
    "normal_filter_pass_count": 0
  },
  {
    "image_path": "Dataset/61.jpeg",
    "inference_time": 1.566441535949707,
    "detections": [
      {
        "confidence": 0.08979777991771698,
        "box": [
          675,
          228,
          724,
          294
        ],
        "aspect_ratio": 0.7424242424242424,
        "area_percentage": 0.764973034345728,
        "would_pass_normal_filters": {
          "aspect_ratio": false,
          "area_percentage": true,
          "confidence": false
        }
      },
      {
        "confidence": 0.06564802676439285,
        "box": [
          665,
          245,
          716,
          289
        ],
        "aspect_ratio": 1.1590909090909092,
        "area_percentage": 0.5307976156684644,
        "would_pass_normal_filters": {
          "aspect_ratio": true,
          "area_percentage": true,
          "confidence": false
        }
      },
      {
        "confidence": 0.036831725388765335,
        "box": [
          676,
          215,
          725,
          281
        ],
        "aspect_ratio": 0.7424242424242424,
        "area_percentage": 0.764973034345728,
        "would_pass_normal_filters": {
          "aspect_ratio": false,
          "area_percentage": true,
          "confidence": false
        }
      },
      {
        "confidence": 0.031742118299007416,
        "box": [
          197,
          68,
          240,
          86
        ],
        "aspect_ratio": 2.388888888888889,
        "area_percentage": 0.1830826000567698,
        "would_pass_normal_filters": {
          "aspect_ratio": true,
          "area_percentage": true,
          "confidence": false
        }
      },
      {
        "confidence": 0.01799740642309189,
        "box": [
          426,
          84,
          504,
          127
        ],
        "aspect_ratio": 1.813953488372093,
        "area_percentage": 0.7933579335793358,
        "would_pass_normal_filters": {
          "aspect_ratio": true,
          "area_percentage": true,
          "confidence": false
        }
      },
      {
        "confidence": 0.013399151153862476,
        "box": [
          331,
          91,
          390,
          123
        ],
        "aspect_ratio": 1.84375,
        "area_percentage": 0.4465890812754282,
        "would_pass_normal_filters": {
          "aspect_ratio": true,
          "area_percentage": true,
          "confidence": false
        }
      },
      {
        "confidence": 0.011810125783085823,
        "box": [
          326,
          79,
          392,
          124
        ],
        "aspect_ratio": 1.4666666666666666,
        "area_percentage": 0.7025262560317911,
        "would_pass_normal_filters": {
          "aspect_ratio": true,
          "area_percentage": true,
          "confidence": false
        }
      }
    ],
    "annotated_image": "direct_61.jpg",
    "high_confidence_count": 0,
    "normal_filter_pass_count": 0
  },
  {
    "image_path": "Dataset/15.jpeg",
    "inference_time": 1.5647976398468018,
    "detections": [
      {
        "confidence": 0.77079176902771,
        "box": [
          295,
          482,
          469,
          522
        ],
        "aspect_ratio": 4.35,
        "area_percentage": 0.8579881656804733,
        "would_pass_normal_filters": {
          "aspect_ratio": true,
          "area_percentage": true,
          "confidence": true
        }
      },
      {
        "confidence": 0.039007097482681274,
        "box": [
          291,
          478,
          469,
          545
        ],
        "aspect_ratio": 2.656716417910448,
        "area_percentage": 1.4701676528599605,
        "would_pass_normal_filters": {
          "aspect_ratio": true,
          "area_percentage": true,
          "confidence": false
        }
      },
      {
        "confidence": 0.03759154677391052,
        "box": [
          359,
          427,
          393,
          461
        ],
        "aspect_ratio": 1.0,
        "area_percentage": 0.14250493096646943,
        "would_pass_normal_filters": {
          "aspect_ratio": true,
          "area_percentage": true,
          "confidence": false
        }
      },
      {
        "confidence": 0.01874421164393425,
        "box": [
          356,
          426,
          404,
          462
        ],
        "aspect_ratio": 1.3333333333333333,
        "area_percentage": 0.21301775147928992,
        "would_pass_normal_filters": {
          "aspect_ratio": true,
          "area_percentage": true,
          "confidence": false
        }
      }
    ],
    "annotated_image": "direct_15.jpg",
    "high_confidence_count": 1,
    "normal_filter_pass_count": 1
  }
]